iaklogger/__init__.py
iaklogger/iaklogger.py
iaklogger/test_iaklogger.py
iaklogger-1.0.7.dist-info/METADATA
iaklogger-1.0.7.dist-info/WHEEL
iaklogger-1.0.7.dist-info/top_level.txt
iaklogger-1.0.7.dist-info/RECORD
