Metadata-Version: 2.1
Name: iaklogger
Version: 1.0.7
Summary: Very basic and easy logger
Home-page: https://github.com/Iakl/iaklogger
Download-URL: https://github.com/Iakl/iaklogger/archive/refs/tags/v1.0.0.tar.gz
Author: Iakl
Author-email: estebaniakl@gmail.com
License: MIT
Keywords: logger,easy,print,log,basic,logging
Classifier: Development Status :: 3 - Alpha
Classifier: Intended Audience :: Developers
Classifier: Topic :: Software Development :: Build Tools
Classifier: License :: OSI Approved :: MIT License
Classifier: Programming Language :: Python :: 3
Classifier: Programming Language :: Python :: 3.4
Classifier: Programming Language :: Python :: 3.5
Classifier: Programming Language :: Python :: 3.6
Classifier: Programming Language :: Python :: 3.7
